{
  "loopReact": "😆",
  "loopDelay": 5,
  "imageProbability": 20,
  "loopMode": "sequential",
  "loopStartMsg": "",
  "loopStopMsg": "",
  "maxLoopCount": 0,
  "autoStopMinutes": 0,
  "ttsLang": "tl",
  "reactOnlyMode": false,
  "pmLoopEnabled": false,
  "pmLoopDelay": 10,
  "pmLoopReact": "❤️",
  "pmLoopMode": "shuffle",
  "pmSearchEnabled": true,
  "pmSearchSource": "quotes",
  "pmSearchCategory": "inspirational",
  "pmSearchPrefix": "",
  "pmSearchSuffix": "",
  "pmAutoReplyOnReceive": false,
  "searchCacheSize": 50,
  "greetNewMembers": false,
  "greetMsg": "Welcome to the group! 👋",
  "antiSpamEnabled": false,
  "antiSpamMaxMsg": 5,
  "antiSpamWindowSec": 10,
  "autoSeenEnabled": false,
  "typingSimulate": false,
  "broadcastMsg": "",
  "broadcastThreads": []
}
